<?xml version="1.0" encoding="UTF-8"?><All><inv><depo><item><matName>Bor</matName><amountt>30</amountt></item><item><matName>Kömür</matName><amountt>4</amountt></item><item><matName>Çelik</matName><amountt>80</amountt></item><item><matName>Para</matName><amountt>624</amountt></item></depo></inv><tiles><building><building_name>KomurFabrika</building_name><building_exp>2</building_exp><building_lvl>1</building_lvl></building><building><building_name>CelikFabrika</building_name><building_exp>3</building_exp><building_lvl>1</building_lvl></building><building><building_name>BorcamFabrikasi</building_name><building_exp>4</building_exp><building_lvl>1</building_lvl></building></tiles><rootShip><ship><ship_part>AnneYakitDeposu</ship_part><ship_partLvl>0</ship_part></ship><ship><ship_part>AnneGovde</ship_part><ship_partLvl>0</ship_part></ship><ship><ship_part>AnneMotor</ship_part><ship_partLvl>0</ship_part></ship></rootShip></All>